vidigi/__init__.py
vidigi/animation.py
vidigi/ciw.py
vidigi/logging.py
vidigi/prep.py
vidigi/process_mapping.py
vidigi/resources.py
vidigi/utils.py
vidigi-1.2.1.dist-info/METADATA
vidigi-1.2.1.dist-info/WHEEL
vidigi-1.2.1.dist-info/licenses/LICENSE.md
vidigi-1.2.1.dist-info/RECORD
