Metadata-Version: 2.4
Name: vidigi
Version: 1.2.1
Summary: A package for creating animated visualisations of queues and pathways from historical data or simulations
Project-URL: Homepage, https://github.com/hsma-tools/vidigi
Project-URL: Documentation, http://hsma-tools.github.io/vidigi/vidigi_docs/
Project-URL: Bug Tracker, https://github.com/hsma-tools/vidigi/issues
Author-email: Sammi Rosser <s.j.rosser@exeter.ac.uk>
License-Expression: MIT
License-File: LICENSE.md
Classifier: License :: OSI Approved :: MIT License
Classifier: Operating System :: OS Independent
Classifier: Programming Language :: Python :: 3.10
Classifier: Programming Language :: Python :: 3.11
Classifier: Programming Language :: Python :: 3.12
Requires-Python: >=3.10
Requires-Dist: graphviz<1.0.0,>=0.15
Requires-Dist: ipycytoscape<2.0.0,>=1.2.0
Requires-Dist: ipywidgets>=8.0.0
Requires-Dist: numpy<3.0.0,>=1.26.2
Requires-Dist: pandas<3.0.0,>=2.0.1
Requires-Dist: plotly<7.0.0,>=5.12.0
Requires-Dist: pydantic<3.0.0,>=2.0.0
Requires-Dist: simpy<5.0.0,>=4.0.0
Requires-Dist: webcolors>=24.11.1
Provides-Extra: streamlit
Requires-Dist: st-cytoscape==0.0.5; extra == 'streamlit'
Requires-Dist: st-javascript==0.1.5; extra == 'streamlit'
